ProjectSystemManager/ProjectManager.py
ProjectSystemManager/__init__.py
ProjectSystemManager/app.py
ProjectSystemManager-0.6.dist-info/LICENSE.txt
ProjectSystemManager-0.6.dist-info/METADATA
ProjectSystemManager-0.6.dist-info/WHEEL
ProjectSystemManager-0.6.dist-info/top_level.txt
ProjectSystemManager-0.6.dist-info/RECORD
