Metadata-Version: 2.1
Name: ProjectSystemManager
Version: 0.6
Summary: ProjectSystemManager is a Python library designed to manage projects by creating, updating, searching, and fetching project details. It allows you to organize projects in a specified directory and store relevant information such as project name, creation date, technologies used, and a summary.
Author: A. Sharan
Author-email: hemsharan3050@gmail.com
License: MIT
Project-URL: Source Repository, https://github.com/AHSharan/ProjectManager/
Project-URL: YouTube, https://www.youtube.com/@A.Sharan
Keywords: project management,python library,project system
Requires-Python: >=3.7
License-File: LICENSE.txt
Requires-Dist: configparser
